{
  "bot_id": "ma_cross",
  "metrics": {
    "total_return": 0.0038649097751881634,
    "annualized_return": 0.13212811351503517,
    "sharpe": 1.615095800136073,
    "sharpe_ci_lo": 1.615095800136073,
    "sharpe_ci_hi": 1.615095800136073,
    "volatility": 0.07685594229746044,
    "max_drawdown": -0.009402792821334232,
    "days": 9,
    "alpha_t_stat_vs_spy": 0.0,
    "alpha_t_stat_vs_qqq": 0.0,
    "significance_weight": 0.0,
    "factor_loadings": {
      "alpha_per_day": 0.0,
      "beta_mkt": 0.0,
      "beta_size": 0.0,
      "beta_value": 0.0,
      "r_squared": 0.0
    }
  },
  "current_weights": {
    "EEM": 0.13572514260793117,
    "EFA": 0.13572507916936638,
    "IWM": 0.13572736136371819,
    "USO": 0.13572861147240078,
    "VNQ": 0.1357205506799729,
    "VTV": 0.13572247598389992,
    "VUG": 0.13572208802426988
  },
  "nav_series": [
    {
      "date": "2026-05-07",
      "nav": 99927.12686998642
    },
    {
      "date": "2026-05-08",
      "nav": 100450.51794429743
    },
    {
      "date": "2026-05-11",
      "nav": 101038.88527327904
    },
    {
      "date": "2026-05-12",
      "nav": 100970.23930982765
    },
    {
      "date": "2026-05-13",
      "nav": 101019.51969634727
    },
    {
      "date": "2026-05-14",
      "nav": 101133.85289647293
    },
    {
      "date": "2026-05-15",
      "nav": 100182.9122304641
    },
    {
      "date": "2026-05-18",
      "nav": 100504.13738765591
    },
    {
      "date": "2026-05-19",
      "nav": 100313.3361994327
    }
  ],
  "daily_returns": [
    {
      "date": "2026-05-08",
      "ret": 0.005237727639182399
    },
    {
      "date": "2026-05-11",
      "ret": 0.005857285169080795
    },
    {
      "date": "2026-05-12",
      "ret": -0.0006794014330792075
    },
    {
      "date": "2026-05-13",
      "ret": 0.00048806843339654904
    },
    {
      "date": "2026-05-14",
      "ret": 0.0011317931471990228
    },
    {
      "date": "2026-05-15",
      "ret": -0.009402792821334272
    },
    {
      "date": "2026-05-18",
      "ret": 0.003206386698490604
    },
    {
      "date": "2026-05-19",
      "ret": -0.0018984411307095828
    }
  ],
  "recent_trades": [
    {
      "bot_id": "ma_cross",
      "symbol": "EEM",
      "side": "BUY",
      "shares": 203.65660461974494,
      "price": 66.63878442227939,
      "slippage_bps": 7.326638695276728,
      "timestamp": "2026-05-07",
      "reason": "rebalance to target weight 0.1357"
    },
    {
      "bot_id": "ma_cross",
      "symbol": "EFA",
      "side": "BUY",
      "shares": 131.8040616208321,
      "price": 102.9666946870745,
      "slippage_bps": 7.454106121198774,
      "timestamp": "2026-05-07",
      "reason": "rebalance to target weight 0.1357"
    },
    {
      "bot_id": "ma_cross",
      "symbol": "HYG",
      "side": "BUY",
      "shares": 169.82770611024262,
      "price": 79.91292399968448,
      "slippage_bps": 6.627020902634633,
      "timestamp": "2026-05-07",
      "reason": "rebalance to target weight 0.1357"
    },
    {
      "bot_id": "ma_cross",
      "symbol": "IWM",
      "side": "BUY",
      "shares": 48.05207483720015,
      "price": 282.43168723532557,
      "slippage_bps": 6.082245580701242,
      "timestamp": "2026-05-07",
      "reason": "rebalance to target weight 0.1357"
    },
    {
      "bot_id": "ma_cross",
      "symbol": "USO",
      "side": "BUY",
      "shares": 100.48404812613158,
      "price": 135.0605277605175,
      "slippage_bps": 6.7071600352390135,
      "timestamp": "2026-05-07",
      "reason": "rebalance to target weight 0.1357"
    },
    {
      "bot_id": "ma_cross",
      "symbol": "VNQ",
      "side": "BUY",
      "shares": 140.64678013173875,
      "price": 96.49299158300464,
      "slippage_bps": 10.684945949618202,
      "timestamp": "2026-05-07",
      "reason": "rebalance to target weight 0.1357"
    },
    {
      "bot_id": "ma_cross",
      "symbol": "VTV",
      "side": "BUY",
      "shares": 65.85119361648651,
      "price": 206.09237017733915,
      "slippage_bps": 8.856612694205868,
      "timestamp": "2026-05-07",
      "reason": "rebalance to target weight 0.1357"
    },
    {
      "bot_id": "ma_cross",
      "symbol": "USO",
      "side": "SELL",
      "shares": 5.524689353899866,
      "price": 144.20196021964816,
      "slippage_bps": 6.7943749158823055,
      "timestamp": "2026-05-12",
      "reason": "rebalance to target weight 0.1357"
    },
    {
      "bot_id": "ma_cross",
      "symbol": "EEM",
      "side": "SELL",
      "shares": 19.937280851463,
      "price": 64.92186100936685,
      "slippage_bps": 7.409606038445116,
      "timestamp": "2026-05-18",
      "reason": "rebalance to target weight 0.1187"
    },
    {
      "bot_id": "ma_cross",
      "symbol": "EFA",
      "side": "SELL",
      "shares": 15.536873188543524,
      "price": 102.58183579982165,
      "slippage_bps": 7.6142469802561425,
      "timestamp": "2026-05-18",
      "reason": "rebalance to target weight 0.1187"
    },
    {
      "bot_id": "ma_cross",
      "symbol": "HYG",
      "side": "SELL",
      "shares": 19.763060421476524,
      "price": 79.48624310118636,
      "slippage_bps": 6.758588599725471,
      "timestamp": "2026-05-18",
      "reason": "rebalance to target weight 0.1187"
    },
    {
      "bot_id": "ma_cross",
      "symbol": "IWM",
      "side": "SELL",
      "shares": 4.79958947748207,
      "price": 275.7999789949119,
      "slippage_bps": 6.160895207420417,
      "timestamp": "2026-05-18",
      "reason": "rebalance to target weight 0.1187"
    },
    {
      "bot_id": "ma_cross",
      "symbol": "USO",
      "side": "SELL",
      "shares": 15.010149733155933,
      "price": 149.18422527191186,
      "slippage_bps": 7.084735680725505,
      "timestamp": "2026-05-18",
      "reason": "rebalance to target weight 0.1187"
    },
    {
      "bot_id": "ma_cross",
      "symbol": "VNQ",
      "side": "SELL",
      "shares": 15.021640695820158,
      "price": 94.90617138522292,
      "slippage_bps": 10.928402133774867,
      "timestamp": "2026-05-18",
      "reason": "rebalance to target weight 0.1187"
    },
    {
      "bot_id": "ma_cross",
      "symbol": "VTV",
      "side": "SELL",
      "shares": 8.297030654786534,
      "price": 207.18452791645643,
      "slippage_bps": 9.426027666771787,
      "timestamp": "2026-05-18",
      "reason": "rebalance to target weight 0.1187"
    },
    {
      "bot_id": "ma_cross",
      "symbol": "VUG",
      "side": "BUY",
      "shares": 136.94266983481762,
      "price": 87.16935699299955,
      "slippage_bps": 9.112488052132104,
      "timestamp": "2026-05-18",
      "reason": "rebalance to target weight 0.1187"
    },
    {
      "bot_id": "ma_cross",
      "symbol": "EEM",
      "side": "BUY",
      "shares": 28.154958966437192,
      "price": 64.3074234688575,
      "slippage_bps": 7.379603338091458,
      "timestamp": "2026-05-19",
      "reason": "rebalance to target weight 0.1357"
    },
    {
      "bot_id": "ma_cross",
      "symbol": "EFA",
      "side": "BUY",
      "shares": 17.318327089823402,
      "price": 101.99746000468562,
      "slippage_bps": 7.600258745286625,
      "timestamp": "2026-05-19",
      "reason": "rebalance to target weight 0.1357"
    },
    {
      "bot_id": "ma_cross",
      "symbol": "HYG",
      "side": "SELL",
      "shares": 150.0646456887661,
      "price": 79.29637882364443,
      "slippage_bps": 6.757359988375216,
      "timestamp": "2026-05-19",
      "reason": "rebalance to target weight 0.0000"
    },
    {
      "bot_id": "ma_cross",
      "symbol": "IWM",
      "side": "BUY",
      "shares": 6.620278127243658,
      "price": 273.16805561,
      "slippage_bps": 6.155883150183392,
      "timestamp": "2026-05-19",
      "reason": "rebalance to target weight 0.1357"
    },
    {
      "bot_id": "ma_cross",
      "symbol": "USO",
      "side": "BUY",
      "shares": 9.063534402957288,
      "price": 153.06892363993484,
      "slippage_bps": 7.12061462388489,
      "timestamp": "2026-05-19",
      "reason": "rebalance to target weight 0.1357"
    },
    {
      "bot_id": "ma_cross",
      "symbol": "VNQ",
      "side": "BUY",
      "shares": 17.265093603111847,
      "price": 95.38401080081336,
      "slippage_bps": 10.916459157122933,
      "timestamp": "2026-05-19",
      "reason": "rebalance to target weight 0.1357"
    },
    {
      "bot_id": "ma_cross",
      "symbol": "VTV",
      "side": "BUY",
      "shares": 8.192284028869093,
      "price": 207.27563025672518,
      "slippage_bps": 9.44699748602884,
      "timestamp": "2026-05-19",
      "reason": "rebalance to target weight 0.1357"
    },
    {
      "bot_id": "ma_cross",
      "symbol": "VUG",
      "side": "BUY",
      "shares": 20.83616086650059,
      "price": 86.36878515810125,
      "slippage_bps": 9.130170557191184,
      "timestamp": "2026-05-19",
      "reason": "rebalance to target weight 0.1357"
    }
  ]
}
